{"content":[{"id":"105fe2b3","settings":{"structure":"20","padding":{"unit":"px","top":"0","right":"0","bottom":"0","left":"0","isLinked":false},"content_position":"middle","padding_tablet":{"unit":"px","top":"15","right":"0","bottom":"0","left":"0","isLinked":false},"padding_mobile":{"unit":"px","top":"15","right":"0","bottom":"0","left":"0","isLinked":false}},"elements":[{"id":"778f5c9","settings":{"_column_size":50,"_inline_size":null,"margin":{"unit":"px","top":"0","right":"15","bottom":"0","left":"0","isLinked":false},"padding":{"unit":"px","top":"15","right":"15","bottom":"15","left":"15","isLinked":false},"box_shadow_hover_box_shadow_type":"yes","box_shadow_hover_box_shadow":{"horizontal":0,"vertical":0,"blur":25,"spread":0,"color":"rgba(0,0,0,0.24)"},"border_hover_transition":{"unit":"px","size":1},"margin_mobile":{"unit":"px","top":"0","right":"0","bottom":"0","left":"0","isLinked":true},"border_radius":{"unit":"px","top":"4","right":"4","bottom":"4","left":"4","isLinked":true}},"elements":[{"id":"48c5f803","settings":{"tabs":[{"tab_title":"\u00bfC\u00f3mo es la entrega en aeropuerto?","tab_content":"<p>La entrega en el aeropuerto es directa, sin&nbsp; intermediarios ni traslados. Una vez que haya llegado a la terminal de \u201cLlegadas\u201d dir\u00edjase hacia al edificio del parking. Tome el ascensor hasta la 4\u00aa planta y nuestro personal le estar\u00e1 esperando en el \u201cMeeting<br>Point\u201d ubicado en el hall.<\/p>","_id":"8917714"}],"icon":"fa fa-arrow-circle-o-right","icon_active":"fa fa-arrow-circle-o-right","border_width":{"unit":"px","size":0},"title_color":"#000000","tab_active_color":"#424242","title_typography_typography":"custom","title_typography_font_size":{"unit":"px","size":18},"title_typography_font_weight":"700","title_typography_text_transform":"uppercase","icon_align":"right","icon_color":"#424242","icon_space":{"unit":"px","size":0},"content_color":"#424242","content_typography_typography":"custom","content_typography_font_size":{"unit":"px","size":16},"content_typography_font_weight":"400","title_typography_line_height_tablet":{"unit":"em","size":1.4},"selected_icon":{"value":"far fa-arrow-alt-circle-right","library":"fa-regular"},"selected_active_icon":{"value":"far fa-arrow-alt-circle-right","library":"fa-regular"},"title_typography_font_family":"Inter","content_typography_font_family":"Inter","__fa4_migrated":{"selected_icon":true,"selected_active_icon":true},"__globals__":{"icon_active_color":"globals\/colors?id=secondary"}},"elements":[],"isInner":false,"widgetType":"accordion","elType":"widget"}],"isInner":true,"elType":"column"},{"id":"3ea458a1","settings":{"_column_size":50,"_inline_size":null,"margin":{"unit":"px","top":"0","right":"15","bottom":"0","left":"0","isLinked":false},"padding":{"unit":"px","top":"15","right":"15","bottom":"15","left":"15","isLinked":false},"box_shadow_hover_box_shadow_type":"yes","box_shadow_hover_box_shadow":{"horizontal":0,"vertical":0,"blur":25,"spread":0,"color":"rgba(0,0,0,0.24)"},"border_hover_transition":{"unit":"px","size":1},"margin_mobile":{"unit":"px","top":"0","right":"0","bottom":"0","left":"0","isLinked":true},"border_radius":{"unit":"px","top":"4","right":"4","bottom":"4","left":"4","isLinked":true}},"elements":[{"id":"1d119ec8","settings":{"tabs":[{"tab_title":"\u00bfTiene un coste adicional el servicio al aeropuerto?","tab_content":"<p>La entrega\/ devoluci\u00f3n en el aeropuerto es <strong>gratuito<\/strong>, exceptuando las entregas de 23h a 8h, que tendr\u00e1n un coste adicional de 30\u20ac y debe ser informada a nuestro personal para obtener las instrucciones sobre c\u00f3mo proceder.<\/p>","_id":"8917714"}],"icon":"fa fa-arrow-circle-o-right","icon_active":"fa fa-arrow-circle-o-right","border_width":{"unit":"px","size":0},"title_color":"#000000","tab_active_color":"#424242","title_typography_typography":"custom","title_typography_font_size":{"unit":"px","size":18},"title_typography_font_weight":"700","title_typography_text_transform":"uppercase","icon_align":"right","icon_color":"#424242","icon_space":{"unit":"px","size":0},"content_color":"#424242","content_typography_typography":"custom","content_typography_font_size":{"unit":"px","size":16},"content_typography_font_weight":"400","title_typography_line_height_tablet":{"unit":"em","size":1.4},"selected_icon":{"value":"far fa-arrow-alt-circle-right","library":"fa-regular"},"selected_active_icon":{"value":"far fa-arrow-alt-circle-right","library":"fa-regular"},"title_typography_font_family":"Inter","content_typography_font_family":"Inter","__fa4_migrated":{"selected_icon":true,"selected_active_icon":true},"__globals__":{"icon_active_color":"globals\/colors?id=secondary"}},"elements":[],"isInner":false,"widgetType":"accordion","elType":"widget"}],"isInner":true,"elType":"column"}],"isInner":true,"elType":"section"}],"page_settings":[],"version":"0.4","title":"Mybooking - Sección - Preguntas frecuentes","type":"section"}